{
  "https://build.chromium.org/p/chromium": {
    "bucket": "ci",
    "builders": [
      "android-archive-dbg",
      "android-archive-rel",
      "linux-archive-dbg",
      "linux-archive-rel",
      "mac-archive-dbg",
      "mac-archive-rel",
      "win-archive-rel",
      "win32-archive-rel"
    ],
    "project": "chromium"
  },
  "https://build.chromium.org/p/chromium.android": {
    "bucket": "ci",
    "builders": [
      "Android ASAN (dbg)",
      "Android WebView L (dbg)",
      "Android WebView M (dbg)",
      "Android WebView N (dbg)",
      "Android WebView O (dbg)",
      "Android arm Builder (dbg)",
      "Android arm64 Builder (dbg)",
      "Android x64 Builder (dbg)",
      "Android x86 Builder (dbg)",
      "Cast Android (dbg)",
      "Deterministic Android",
      "Deterministic Android (dbg)",
      "KitKat Phone Tester (dbg)",
      "KitKat Tablet Tester",
      "Lollipop Phone Tester",
      "Lollipop Tablet Tester",
      "Marshmallow 64 bit Tester",
      "Marshmallow Tablet Tester",
      "Nougat Phone Tester",
      "Oreo Phone Tester",
      "android-cronet-arm-dbg",
      "android-cronet-arm-rel",
      "android-cronet-arm64-dbg",
      "android-cronet-arm64-rel",
      "android-cronet-asan-arm-rel",
      "android-cronet-kitkat-arm-rel",
      "android-cronet-lollipop-arm-rel",
      "android-cronet-marshmallow-arm64-perf-rel",
      "android-cronet-marshmallow-arm64-rel",
      "android-cronet-x86-dbg",
      "android-cronet-x86-rel",
      "android-incremental-dbg",
      "android-jumbo-rel",
      "android-kitkat-arm-rel",
      "android-marshmallow-arm64-rel",
      "android-oreo-arm64-rel",
      "android-pie-arm64-dbg"
    ],
    "project": "chromium"
  },
  "https://build.chromium.org/p/chromium.android.fyi": {
    "bucket": "ci",
    "builders": [
      "Android WebView O NetworkService (dbg)",
      "Memory Infra Tester",
      "android-pie-x86-fyi-rel"
    ],
    "project": "chromium"
  },
  "https://build.chromium.org/p/chromium.chromiumos": {
    "bucket": "ci",
    "builders": [
      "Linux ChromiumOS Full",
      "chromeos-amd64-generic-asan-rel",
      "chromeos-amd64-generic-cfi-thin-lto-rel",
      "chromeos-amd64-generic-rel",
      "chromeos-arm-generic-rel",
      "chromeos-kevin-rel",
      "linux-chromeos-dbg",
      "linux-chromeos-rel"
    ],
    "project": "chromium"
  },
  "https://build.chromium.org/p/chromium.clang": {
    "bucket": "ci",
    "builders": [
      "ToTLinuxOfficial",
      "ToTMacOfficial",
      "ToTWin",
      "ToTWin64",
      "ToTWinOfficial",
      "ToTWinThinLTO64",
      "CFI Linux CF",
      "CFI Linux ToT",
      "CrWinAsan",
      "CrWinAsan(dll)",
      "ToTAndroid",
      "ToTAndroid (dbg)",
      "ToTAndroid x64",
      "ToTAndroid64",
      "ToTAndroidASan",
      "ToTAndroidCFI",
      "ToTAndroidOfficial",
      "ToTLinux",
      "ToTLinux (dbg)",
      "ToTLinuxASan",
      "ToTLinuxASanLibfuzzer",
      "ToTLinuxCoverage",
      "ToTLinuxMSan",
      "ToTLinuxTSan",
      "ToTLinuxThinLTO",
      "ToTLinuxUBSanVptr",
      "ToTMac",
      "ToTMac (dbg)",
      "ToTMacASan",
      "ToTMacCoverage",
      "ToTWin(dbg)",
      "ToTWin(dll)",
      "ToTWin64(dbg)",
      "ToTWin64(dll)",
      "ToTWinASanLibfuzzer",
      "ToTWinCFI",
      "ToTWinCFI64",
      "ToTWinLibcxx64",
      "ToTiOS",
      "ToTiOSDevice",
      "UBSanVptr Linux",
      "linux-win_cross-rel"
    ],
    "project": "chromium"
  },
  "https://build.chromium.org/p/chromium.fyi": {
    "bucket": "ci",
    "builders": [
      "Android Builder (dbg) Goma Canary",
      "Closure Compilation Linux",
      "Deterministic Fuchsia (dbg)",
      "Jumbo Linux x64",
      "Jumbo Mac",
      "Jumbo Win x64",
      "Linux Builder Goma Canary",
      "Linux Viz",
      "Linux remote_run Builder",
      "Linux remote_run Tester",
      "Linux x64 Goma Canary (clobber)",
      "Linux x64 Goma Canary LocalOutputCache",
      "Mac Builder (dbg) Goma Canary",
      "Mac Builder (dbg) Goma Canary (clobber)",
      "Mac Builder Goma Canary",
      "Mac Goma Canary (clobber)",
      "Mac Goma Canary LocalOutputCache",
      "Mac deterministic",
      "Mac deterministic (dbg)",
      "Mojo Android",
      "Mojo ChromiumOS",
      "Mojo Linux",
      "Mojo Windows",
      "Site Isolation Android",
      "VR Linux",
      "Win 10 Fast Ring",
      "Win Builder (dbg) Goma Canary",
      "Win Builder Goma Canary",
      "Win Goma Canary LocalOutputCache",
      "Win cl.exe Goma Canary LocalOutputCache",
      "Win7 Builder (dbg) Goma Canary",
      "Win7 Builder Goma Canary",
      "WinMSVC64 Goma Canary",
      "android-code-coverage",
      "android-mojo-webview-rel",
      "chromeos-amd64-generic-rel-goma-canary",
      "chromeos-amd64-generic-rel-vm-tests",
      "chromeos-kevin-rel-hw-tests",
      "chromeos-vm-code-coverage",
      "fuchsia-fyi-arm64-rel",
      "fuchsia-fyi-x64-dbg",
      "fuchsia-fyi-x64-rel",
      "ios-device-goma-canary-clobber",
      "ios-simulator-code-coverage",
      "ios-simulator-cronet",
      "ios12-beta-simulator",
      "ios13-beta-simulator",
      "ios13-sdk-device",
      "ios13-sdk-simulator",
      "linux-annotator-rel",
      "linux-blink-animation-use-time-delta",
      "linux-blink-heap-concurrent-marking-tsan-rel",
      "linux-blink-heap-unified-gc",
      "linux-blink-heap-verification",
      "linux-chromeos-code-coverage",
      "linux-chromeos-oobe-code-coverage",
      "linux-chromium-tests-staging-builder",
      "linux-chromium-tests-staging-tests",
      "linux-code-coverage",
      "linux-fieldtrial-rel",
      "linux-wpt-fyi-rel",
      "mac-code-coverage-generation",
      "mac-hermetic-upgrade-rel",
      "mac-jumbo-rel",
      "mac-mojo-rel",
      "mac-osxbeta-rel",
      "win-annotator-rel",
      "win-celab-builder-rel",
      "win-celab-tester-rel",
      "win-jumbo-rel",
      "win-pixel-builder-rel",
      "win-pixel-tester-rel"
    ],
    "project": "chromium"
  },
  "https://build.chromium.org/p/chromium.gpu": {
    "bucket": "ci",
    "builders": [
      "Android Release (Nexus 5X)",
      "GPU Linux Builder",
      "GPU Linux Builder (dbg)",
      "GPU Mac Builder",
      "GPU Mac Builder (dbg)",
      "GPU Win Builder",
      "GPU Win Builder (dbg)",
      "Linux Debug (NVIDIA)",
      "Linux Release (NVIDIA)",
      "Mac Debug (Intel)",
      "Mac Release (Intel)",
      "Mac Retina Debug (AMD)",
      "Mac Retina Release (AMD)",
      "Win10 Debug (NVIDIA)",
      "Win10 Release (NVIDIA)"
    ],
    "project": "chromium"
  },
  "https://build.chromium.org/p/chromium.infra": {
    "bucket": "ci",
    "builders": [
      "build-recipes-tests",
      "depot_tools zip uploader",
      "depot_tools-recipes-tests",
      "infra-continuous-mac-10.12-64",
      "infra-continuous-mac-10.13-64",
      "infra-continuous-recipes-tests",
      "infra-continuous-trusty-64",
      "infra-continuous-win10-64",
      "infra-continuous-win7-64",
      "infra-continuous-xenial-64",
      "infra-continuous-yakkety-64",
      "infra-continuous-zesty-64",
      "luci-gae-continuous-mac",
      "luci-gae-continuous-trusty-64",
      "luci-gae-continuous-win",
      "luci-go-continuous-mac-10.13-64",
      "luci-go-continuous-trusty-64",
      "luci-go-continuous-win10-64",
      "luci-go-continuous-win7-64",
      "luci-go-continuous-xenial-64",
      "recipe_engine-recipes-tests"
    ],
    "project": "infra"
  },
  "https://build.chromium.org/p/chromium.infra.cron": {
    "bucket": "cron",
    "builders": [
      "Build From Tarball",
      "Chromium Gatekeeper",
      "chromium-lkgr-finder",
      "cros-dut-flash",
      "cros-flash-scheduler-kevin",
      "gsubtreed-aosp-platform-system-core",
      "gsubtreed-chromium",
      "gsubtreed-chromiumos-platform2",
      "gsubtreed-infra",
      "gsubtreed-llvm-clang",
      "gsubtreed-luci-py",
      "gsubtreed-selenium",
      "publish_tarball",
      "publish_tarball_dispatcher",
      "wpt-exporter",
      "wpt-importer"
    ],
    "project": "infra"
  },
  "https://build.chromium.org/p/chromium.linux": {
    "bucket": "ci",
    "builders": [
      "Cast Audio Linux",
      "Cast Linux",
      "Deterministic Linux",
      "Deterministic Linux (dbg)",
      "Fuchsia ARM64",
      "Fuchsia x64",
      "Leak Detection Linux",
      "Linux Builder",
      "Linux Builder (dbg)",
      "Linux Builder (dbg)(32)",
      "Linux Tests",
      "Linux Tests (dbg)(1)",
      "fuchsia-arm64-cast",
      "fuchsia-x64-cast",
      "linux-gcc-rel",
      "linux-jumbo-rel",
      "linux-ozone-rel",
      "linux-trusty-rel"
    ],
    "project": "chromium"
  },
  "https://build.chromium.org/p/chromium.mac": {
    "bucket": "ci",
    "builders": [
      "Mac Builder",
      "Mac Builder (dbg)",
      "Mac10.10 Tests",
      "Mac10.11 Tests",
      "Mac10.12 Tests",
      "Mac10.13 Tests",
      "Mac10.13 Tests (dbg)",
      "WebKit Mac10.13 (retina)",
      "ios-device",
      "ios-device-xcode-clang",
      "ios-simulator",
      "ios-simulator-full-configs",
      "ios-simulator-xcode-clang",
      "ios-slimnav"
    ],
    "project": "chromium"
  },
  "https://build.chromium.org/p/chromium.memory": {
    "bucket": "ci",
    "builders": [
      "Android CFI",
      "Linux ASan LSan Builder",
      "Linux ASan LSan Tests (1)",
      "Linux ASan Tests (sandboxed)",
      "Linux CFI",
      "Linux Chromium OS ASan LSan Builder",
      "Linux Chromium OS ASan LSan Tests (1)",
      "Linux ChromiumOS MSan Builder",
      "Linux ChromiumOS MSan Tests",
      "Linux MSan Builder",
      "Linux MSan Tests",
      "Linux TSan Builder",
      "Linux TSan Tests",
      "Mac ASan 64 Builder",
      "Mac ASan 64 Tests (1)",
      "WebKit Linux ASAN",
      "WebKit Linux Leak",
      "WebKit Linux MSAN",
      "android-asan",
      "win-asan"
    ],
    "project": "chromium"
  },
  "https://build.chromium.org/p/chromium.perf": {
    "bucket": "ci",
    "builders": [
      "Android Nexus5 Perf",
      "Android Nexus5X WebView Perf",
      "Android Nexus6 WebView Perf",
      "Win 7 Nvidia GPU Perf",
      "Win 7 Perf",
      "android-builder-perf",
      "android-go-perf",
      "android-go_webview-perf",
      "android-nexus5x-perf",
      "android-pixel2-perf",
      "android-pixel2_webview-perf",
      "android_arm64-builder-perf",
      "linux-builder-perf",
      "linux-perf",
      "mac-10_12_laptop_low_end-perf",
      "mac-10_13_laptop_high_end-perf",
      "mac-builder-perf",
      "win-10-perf",
      "win32-builder-perf",
      "win64-builder-perf"
    ],
    "project": "chrome"
  },
  "https://build.chromium.org/p/chromium.tools.build": {
    "bucket": "ci",
    "builders": [],
    "project": "chromium"
  },
  "https://build.chromium.org/p/chromium.webkit": {
    "bucket": "ci",
    "builders": [
      "WebKit Linux Trusty ASAN",
      "WebKit Linux Trusty Leak",
      "WebKit Linux Trusty MSAN",
      "WebKit Mac10.13 (retina)",
      "WebKit Win10"
    ],
    "project": "chromium"
  },
  "https://build.chromium.org/p/chromium.win": {
    "bucket": "ci",
    "builders": [
      "WebKit Win10",
      "Win 7 Tests x64 (1)",
      "Win Builder",
      "Win Builder (dbg)",
      "Win x64 Builder",
      "Win x64 Builder (dbg)",
      "Win10 Tests x64",
      "Win10 Tests x64 (dbg)",
      "Win7 (32) Tests",
      "Win7 Tests (1)",
      "Win7 Tests (dbg)(1)",
      "Windows deterministic"
    ],
    "project": "chromium"
  },
  "https://build.chromium.org/p/client.boringssl": {
    "bucket": "ci",
    "builders": [
      "android_aarch64",
      "android_aarch64_rel",
      "android_arm",
      "android_arm_rel",
      "docs",
      "ios64_compile",
      "ios_compile",
      "linux",
      "linux32",
      "linux32_rel",
      "linux32_sde",
      "linux_clang_cfi",
      "linux_clang_rel",
      "linux_clang_rel_msan",
      "linux_clang_rel_tsan",
      "linux_fips",
      "linux_fips_clang",
      "linux_fips_clang_rel",
      "linux_fips_noasm_asan",
      "linux_fips_rel",
      "linux_fuzz",
      "linux_noasm_asan",
      "linux_nothreads",
      "linux_rel",
      "linux_sde",
      "linux_shared",
      "linux_small",
      "mac",
      "mac_rel",
      "mac_small",
      "win32",
      "win32_nasm",
      "win32_rel",
      "win32_small",
      "win32_vs2017",
      "win32_vs2017_clang",
      "win64",
      "win64_nasm",
      "win64_rel",
      "win64_small",
      "win64_vs2017",
      "win64_vs2017_clang"
    ],
    "project": "boringssl"
  },
  "https://build.chromium.org/p/client.catapult": {
    "bucket": "ci",
    "builders": [],
    "project": "catapult"
  },
  "https://build.chromium.org/p/client.crashpad": {
    "bucket": "ci",
    "builders": [
      "crashpad_fuchsia_arm64_dbg",
      "crashpad_fuchsia_arm64_rel",
      "crashpad_fuchsia_x64_dbg",
      "crashpad_fuchsia_x64_rel",
      "crashpad_linux_dbg",
      "crashpad_linux_rel",
      "crashpad_mac_dbg",
      "crashpad_mac_rel",
      "crashpad_win_dbg",
      "crashpad_win_rel"
    ],
    "project": "crashpad"
  },
  "https://build.chromium.org/p/client.nacl": {
    "bucket": "ci",
    "builders": [
      "linux-32-glibc-dbg",
      "linux-32-glibc-opt",
      "linux-32-newlib-dbg",
      "linux-32-newlib-opt",
      "linux-64-arm-glibc-opt",
      "linux-64-arm-newlib-opt",
      "linux-64-glibc-dbg",
      "linux-64-glibc-opt",
      "linux-64-newlib-dbg",
      "linux-64-newlib-opt",
      "linux-64-newlib-opt-test",
      "linux-64-validator-opt",
      "linux_64-newlib-arm_qemu-pnacl-buildonly-spec",
      "linux_64-newlib-arm_qemu-pnacl-dbg",
      "linux_64-newlib-arm_qemu-pnacl-opt",
      "linux_64-newlib-dbg-asan",
      "linux_64-newlib-mips-pnacl",
      "linux_64-newlib-x86_32-pnacl",
      "linux_64-newlib-x86_32-pnacl-spec",
      "linux_64-newlib-x86_32-spec",
      "linux_64-newlib-x86_64-pnacl",
      "linux_64-newlib-x86_64-pnacl-spec",
      "linux_64-newlib-x86_64-spec",
      "mac-arm-newlib-opt",
      "mac-glibc-dbg",
      "mac-glibc-opt",
      "mac-newlib-dbg",
      "mac-newlib-opt",
      "mac-newlib-opt-pnacl",
      "oneiric_32-newlib-arm_hw-pnacl-panda-dbg",
      "oneiric_32-newlib-arm_hw-pnacl-panda-opt",
      "oneiric_32-newlib-arm_hw-pnacl-panda-spec",
      "win7-64-arm-newlib-opt",
      "win7-64-glibc-dbg",
      "win7-64-glibc-opt",
      "win7-64-newlib-opt-pnacl",
      "win8-64-newlib-dbg",
      "win8-64-newlib-opt"
    ],
    "project": "nacl"
  },
  "https://build.chromium.org/p/client.pdfium": {
    "bucket": "ci",
    "builders": [
      "android",
      "android_no_v8",
      "linux",
      "linux_asan_lsan",
      "linux_msan",
      "linux_no_v8",
      "linux_ubsan",
      "linux_xfa",
      "linux_xfa_asan_lsan",
      "linux_xfa_component",
      "linux_xfa_jumbo",
      "linux_xfa_msan",
      "linux_xfa_rel",
      "linux_xfa_ubsan",
      "mac",
      "mac_no_v8",
      "mac_xfa",
      "mac_xfa_component",
      "mac_xfa_jumbo",
      "mac_xfa_rel",
      "win",
      "win_asan",
      "win_no_v8",
      "win_xfa",
      "win_xfa_32",
      "win_xfa_asan",
      "win_xfa_component",
      "win_xfa_jumbo",
      "win_xfa_msvc",
      "win_xfa_msvc_32",
      "win_xfa_rel"
    ],
    "project": "pdfium"
  },
  "https://build.chromium.org/p/client.v8": {
    "bucket": "ci",
    "builders": [
      "V8 Fuchsia",
      "V8 Fuchsia - debug",
      "V8 Fuzzer",
      "V8 Linux",
      "V8 Linux - arm64 - sim - MSAN",
      "V8 Linux - builder",
      "V8 Linux - debug",
      "V8 Linux - debug builder",
      "V8 Linux - gc stress",
      "V8 Linux - noi18n - debug",
      "V8 Linux - nosnap",
      "V8 Linux - nosnap - debug",
      "V8 Linux - nosnap builder",
      "V8 Linux - nosnap debug builder",
      "V8 Linux - shared",
      "V8 Linux - verify csa",
      "V8 Linux gcc",
      "V8 Linux64",
      "V8 Linux64 - builder",
      "V8 Linux64 - cfi",
      "V8 Linux64 - custom snapshot - debug",
      "V8 Linux64 - custom snapshot - debug builder",
      "V8 Linux64 - debug",
      "V8 Linux64 - debug - header includes",
      "V8 Linux64 - debug builder",
      "V8 Linux64 - internal snapshot",
      "V8 Linux64 - pointer compression",
      "V8 Linux64 - shared",
      "V8 Linux64 - verify csa",
      "V8 Linux64 ASAN",
      "V8 Linux64 GC Stress - custom snapshot",
      "V8 Linux64 Jumbo",
      "V8 Linux64 Jumbo - debug",
      "V8 Linux64 Jumbo - limited",
      "V8 Linux64 Jumbo - limited - debug",
      "V8 Linux64 TSAN",
      "V8 Linux64 TSAN - builder",
      "V8 Linux64 TSAN - concurrent marking",
      "V8 Linux64 TSAN - isolates",
      "V8 Linux64 UBSan",
      "V8 Linux64 gcc - debug",
      "V8 Mac64",
      "V8 Mac64 - debug",
      "V8 Mac64 ASAN",
      "V8 Mac64 GC Stress",
      "V8 Presubmit",
      "V8 Win32",
      "V8 Win32 - builder",
      "V8 Win32 - debug",
      "V8 Win32 - debug builder",
      "V8 Win32 - nosnap - shared",
      "V8 Win64",
      "V8 Win64 - debug",
      "V8 Win64 - msvc",
      "V8 Win64 ASAN"
    ],
    "project": "v8"
  },
  "https://build.chromium.org/p/client.v8.chromium": {
    "bucket": "ci",
    "builders": [
      "Linux - Future",
      "Linux - Future (dbg)",
      "Linux V8 API Stability"
    ],
    "project": "v8"
  },
  "https://build.chromium.org/p/client.v8.fyi": {
    "bucket": "ci",
    "builders": [
      "Android Builder",
      "Android V8 FYI Release (Nexus 5X)",
      "Linux ASAN Builder",
      "Linux Debug Builder",
      "Linux Snapshot Builder",
      "Linux Tests (dbg)(1)",
      "Linux V8 FYI Release (NVIDIA)",
      "Linux V8 FYI Release - pointer compression (NVIDIA)",
      "Mac V8 FYI Release (Intel)",
      "V8 Android GN (dbg)",
      "V8 Linux - full debug",
      "V8 Linux - noembed",
      "V8 Linux - noembed - debug",
      "V8 Linux - predictable",
      "V8 Linux - vtunejit",
      "V8 Linux GN",
      "V8 Linux64 - debug - fyi",
      "V8 Linux64 - debug - perfetto",
      "V8 Linux64 - debug - perfetto - builder",
      "V8 Linux64 - fyi",
      "V8 Linux64 - gcov coverage",
      "V8 Linux64 - node.js integration ng",
      "V8 iOS - sim",
      "V8 Blink Linux",
      "V8 Blink Linux Debug",
      "V8 Blink Mac",
      "V8 Blink Win",
      "V8-Blink Linux 64",
      "V8-Blink Linux 64 - future",
      "Win V8 FYI Release (NVIDIA)"
    ],
    "project": "v8"
  },
  "https://build.chromium.org/p/client.v8.ports": {
    "bucket": "ci",
    "builders": [
      "V8 Android Arm - builder",
      "V8 Android Arm64 - N5X",
      "V8 Android Arm64 - builder",
      "V8 Android Arm64 - debug builder",
      "V8 Arm",
      "V8 Arm - builder",
      "V8 Arm - debug",
      "V8 Arm - debug builder",
      "V8 Arm GC Stress",
      "V8 Arm64 - builder",
      "V8 Linux - arm - sim",
      "V8 Linux - arm - sim - debug",
      "V8 Linux - arm - sim - lite",
      "V8 Linux - arm - sim - lite - debug",
      "V8 Linux - arm64 - sim",
      "V8 Linux - arm64 - sim - debug",
      "V8 Linux - arm64 - sim - gc stress",
      "V8 Linux - mips64el - sim",
      "V8 Linux - mips64el - sim - builder",
      "V8 Linux - mipsel - sim",
      "V8 Linux - mipsel - sim - builder",
      "V8 Linux - ppc64 - sim",
      "V8 Linux - s390x - sim",
      "V8 Linux64 - arm64 - sim - pointer compression",
      "V8 Linux64 - arm64 - sim - pointer compression - builder",
      "V8 Mips - big endian - nosnap",
      "V8 Mips - builder"
    ],
    "project": "v8"
  },
  "https://build.chromium.org/p/client.webrtc": {
    "bucket": "ci",
    "builders": [
      "Android32 (M Nexus5X)",
      "Android32 (M Nexus5X)(dbg)",
      "Android32 (more configs)",
      "Android32 Builder arm",
      "Android32 Builder x86",
      "Android32 Builder x86 (dbg)",
      "Android64 (M Nexus5X)",
      "Android64 (M Nexus5X)(dbg)",
      "Android64 Builder arm64",
      "Android64 Builder x64 (dbg)",
      "Linux (more configs)",
      "Linux Asan",
      "Linux MSan",
      "Linux Tsan v2",
      "Linux UBSan",
      "Linux UBSan vptr",
      "Linux32 Debug",
      "Linux32 Debug (ARM)",
      "Linux32 Release",
      "Linux32 Release (ARM)",
      "Linux64 Builder",
      "Linux64 Debug",
      "Linux64 Debug (ARM)",
      "Linux64 Release",
      "Linux64 Release (ARM)",
      "Linux64 Release (GCC)",
      "Linux64 Release (Libfuzzer)",
      "Mac Asan",
      "Mac64 Debug",
      "Mac64 Release",
      "Win (more configs)",
      "Win32 Debug",
      "Win32 Debug (Clang)",
      "Win32 Release",
      "Win32 Release (Clang)",
      "Win64 ASan",
      "Win64 Debug",
      "Win64 Debug (Clang)",
      "Win64 Release",
      "Win64 Release (Clang)",
      "iOS API Framework Builder",
      "iOS32 Debug",
      "iOS32 Release",
      "iOS64 Debug",
      "iOS64 Release",
      "iOS64 Sim Debug (iOS 10.0)",
      "iOS64 Sim Debug (iOS 11)",
      "iOS64 Sim Debug (iOS 12)"
    ],
    "project": "webrtc"
  },
  "https://build.chromium.org/p/tryserver.chromium.linux": {
    "bucket": "try",
    "builders": [
      "cast_shell_audio_linux",
      "cast_shell_linux",
      "chromium_presubmit",
      "closure_compilation",
      "fuchsia-arm64-cast",
      "fuchsia-fyi-arm64-rel",
      "fuchsia-fyi-x64-dbg",
      "fuchsia-fyi-x64-rel",
      "fuchsia-x64-cast",
      "fuchsia_arm64",
      "fuchsia_x64",
      "gpu-fyi-try-linux-intel-dqp",
      "gpu-fyi-try-linux-intel-exp",
      "gpu-fyi-try-linux-intel-rel",
      "gpu-fyi-try-linux-nvidia-dbg",
      "gpu-fyi-try-linux-nvidia-dqp",
      "gpu-fyi-try-linux-nvidia-exp",
      "gpu-fyi-try-linux-nvidia-rel",
      "gpu-fyi-try-linux-nvidia-skv",
      "gpu-fyi-try-linux-nvidia-tsn",
      "gpu-try-linux-nvidia-dbg",
      "gpu-try-linux-nvidia-rel",
      "layout_test_leak_detection",
      "leak_detection_linux",
      "linux-annotator-rel",
      "linux-gcc-rel",
      "linux-libfuzzer-asan-rel",
      "linux-ozone-rel",
      "linux-rel",
      "linux-trusty-rel",
      "linux_arm",
      "linux_chromium_analysis",
      "linux_chromium_archive_rel_ng",
      "linux_chromium_asan_rel_ng",
      "linux_chromium_cfi_rel_ng",
      "linux_chromium_chromeos_asan_rel_ng",
      "linux_chromium_chromeos_msan_rel_ng",
      "linux_chromium_clobber_rel_ng",
      "linux_chromium_compile_dbg_32_ng",
      "linux_chromium_component_updater",
      "linux_chromium_msan_rel_ng",
      "linux_chromium_tsan_rel_ng",
      "linux_chromium_ubsan_rel_ng",
      "linux_layout_tests_composite_after_paint",
      "linux_layout_tests_layout_ng",
      "linux_mojo",
      "linux_mojo_chromeos",
      "linux_optional_gpu_tests_rel",
      "linux_upload_clang",
      "linux_vr"
    ],
    "project": "chromium"
  }
}
