[
  {
    "cmd": [
      "python",
      "-u",
      "RECIPE_MODULE[depot_tools::bot_update]\\resources\\bot_update.py",
      "--spec",
      "cache_dir = '[GIT_CACHE]'\nsolutions = [{'deps_file': 'tools/deps/dartium.deps/DEPS', 'managed': False, 'name': 'src/dart', 'url': 'https://chromium.googlesource.com/external/github.com/dart-lang/sdk.git'}]",
      "--patch_root",
      "src/dart",
      "--revision_mapping_file",
      "{}",
      "--git-cache-dir",
      "[GIT_CACHE]",
      "--output_json",
      "/path/to/tmp/json",
      "--revision",
      "src/dart@12345",
      "--output_manifest"
    ],
    "env": {
      "PATH": "%(PATH)s;RECIPE_PACKAGE_REPO[depot_tools]"
    },
    "name": "bot_update",
    "~followup_annotations": [
      "@@@STEP_TEXT@Some step text@@@",
      "@@@STEP_LOG_LINE@json.output@{@@@",
      "@@@STEP_LOG_LINE@json.output@  \"did_run\": true, @@@",
      "@@@STEP_LOG_LINE@json.output@  \"fixed_revisions\": {@@@",
      "@@@STEP_LOG_LINE@json.output@    \"src/dart\": \"12345\"@@@",
      "@@@STEP_LOG_LINE@json.output@  }, @@@",
      "@@@STEP_LOG_LINE@json.output@  \"manifest\": {}, @@@",
      "@@@STEP_LOG_LINE@json.output@  \"patch_failure\": false, @@@",
      "@@@STEP_LOG_LINE@json.output@  \"patch_root\": \"src/dart\", @@@",
      "@@@STEP_LOG_LINE@json.output@  \"properties\": {}, @@@",
      "@@@STEP_LOG_LINE@json.output@  \"root\": \"src/dart\", @@@",
      "@@@STEP_LOG_LINE@json.output@  \"step_text\": \"Some step text\"@@@",
      "@@@STEP_LOG_LINE@json.output@}@@@",
      "@@@STEP_LOG_END@json.output@@@"
    ]
  },
  {
    "cmd": [
      "python",
      "-u",
      "RECIPE_PACKAGE_REPO[depot_tools]\\gclient.py",
      "runhooks"
    ],
    "cwd": "[START_DIR]\\src/dart",
    "env": {
      "GYP_DEFINES": "component=static_library linux_strip_binary fastbuild=1 target_arch=ia32",
      "GYP_GENERATORS": "ninja",
      "PATH": "%(PATH)s;RECIPE_PACKAGE_REPO[depot_tools]"
    },
    "name": "gclient runhooks"
  },
  {
    "cmd": [
      "python",
      "-u",
      "[START_DIR]\\src\\dart\\tools\\task_kill.py",
      "--kill_browsers=True"
    ],
    "cwd": "[START_DIR]\\src",
    "name": "taskkill before building"
  },
  {
    "cmd": [
      "python",
      "-u",
      "[START_DIR]\\src\\dart\\tools\\dartium\\build.py",
      "--mode=Release"
    ],
    "cwd": "[START_DIR]\\src",
    "env": {
      "GYP_DEFINES": "component=static_library linux_strip_binary fastbuild=1 target_arch=ia32",
      "GYP_GENERATORS": "ninja"
    },
    "name": "build dartium"
  },
  {
    "cmd": [
      "python",
      "-u",
      "[START_DIR]\\src\\dart\\tools\\dartium\\buildbot_annotated_steps.py"
    ],
    "cwd": "[START_DIR]\\src",
    "name": "annotated steps"
  },
  {
    "cmd": [
      "python",
      "-u",
      "[START_DIR]\\src\\dart\\tools\\task_kill.py",
      "--kill_browsers=True"
    ],
    "cwd": "[START_DIR]\\src",
    "name": "taskkill after building"
  },
  {
    "cmd": [
      "python",
      "-u",
      "\nimport os, sys\nfrom common import chromium_utils # Error? See https://crbug.com/584783.\n\n\nif os.path.exists(sys.argv[1]):\n  chromium_utils.RemoveDirectory(sys.argv[1])\n",
      "[START_DIR]\\src\\out"
    ],
    "name": "rmtree clobber",
    "~followup_annotations": [
      "@@@STEP_LOG_LINE@python.inline@@@@",
      "@@@STEP_LOG_LINE@python.inline@import os, sys@@@",
      "@@@STEP_LOG_LINE@python.inline@from common import chromium_utils # Error? See https://crbug.com/584783.@@@",
      "@@@STEP_LOG_LINE@python.inline@@@@",
      "@@@STEP_LOG_LINE@python.inline@@@@",
      "@@@STEP_LOG_LINE@python.inline@if os.path.exists(sys.argv[1]):@@@",
      "@@@STEP_LOG_LINE@python.inline@  chromium_utils.RemoveDirectory(sys.argv[1])@@@",
      "@@@STEP_LOG_END@python.inline@@@"
    ]
  },
  {
    "name": "$result",
    "recipe_result": null,
    "status_code": 0
  }
]