[
  {
    "cmd": [],
    "name": "get linux_warmed"
  },
  {
    "cmd": [
      "led",
      "get-builder",
      "luci.chromium.try:linux_warmed"
    ],
    "env": {
      "SWARMING_TASK_ID": null
    },
    "name": "get linux_warmed.led get-builder",
    "~followup_annotations": [
      "@@@STEP_NEST_LEVEL@1@@@",
      "@@@STEP_LOG_LINE@proto.output@{@@@",
      "@@@STEP_LOG_LINE@proto.output@  \"buildbucket\": {@@@",
      "@@@STEP_LOG_LINE@proto.output@    \"bbagent_args\": {@@@",
      "@@@STEP_LOG_LINE@proto.output@      \"build\": {@@@",
      "@@@STEP_LOG_LINE@proto.output@        \"builder\": {@@@",
      "@@@STEP_LOG_LINE@proto.output@          \"bucket\": \"try\",@@@",
      "@@@STEP_LOG_LINE@proto.output@          \"builder\": \"linux_warmed\",@@@",
      "@@@STEP_LOG_LINE@proto.output@          \"project\": \"chromium\"@@@",
      "@@@STEP_LOG_LINE@proto.output@        }@@@",
      "@@@STEP_LOG_LINE@proto.output@      }@@@",
      "@@@STEP_LOG_LINE@proto.output@    }@@@",
      "@@@STEP_LOG_LINE@proto.output@  }@@@",
      "@@@STEP_LOG_LINE@proto.output@}@@@",
      "@@@STEP_LOG_END@proto.output@@@"
    ]
  },
  {
    "cmd": [
      "led",
      "edit",
      "-name",
      "led: warm linux_warmed"
    ],
    "env": {
      "SWARMING_TASK_ID": null
    },
    "name": "get linux_warmed.led edit",
    "stdin": "{\n\"buildbucket\": {\n\"bbagent_args\": {\n\"build\": {\n\"builder\": {\n\"bucket\": \"try\", \n\"builder\": \"linux_warmed\", \n\"project\": \"chromium\"\n}\n}\n}\n}\n}",
    "~followup_annotations": [
      "@@@STEP_NEST_LEVEL@1@@@",
      "@@@STEP_LOG_LINE@proto.output@{@@@",
      "@@@STEP_LOG_LINE@proto.output@  \"buildbucket\": {@@@",
      "@@@STEP_LOG_LINE@proto.output@    \"bbagent_args\": {@@@",
      "@@@STEP_LOG_LINE@proto.output@      \"build\": {@@@",
      "@@@STEP_LOG_LINE@proto.output@        \"builder\": {@@@",
      "@@@STEP_LOG_LINE@proto.output@          \"bucket\": \"try\",@@@",
      "@@@STEP_LOG_LINE@proto.output@          \"builder\": \"linux_warmed\",@@@",
      "@@@STEP_LOG_LINE@proto.output@          \"project\": \"chromium\"@@@",
      "@@@STEP_LOG_LINE@proto.output@        }@@@",
      "@@@STEP_LOG_LINE@proto.output@      }@@@",
      "@@@STEP_LOG_LINE@proto.output@    },@@@",
      "@@@STEP_LOG_LINE@proto.output@    \"name\": \"led: warm linux_warmed\"@@@",
      "@@@STEP_LOG_LINE@proto.output@  }@@@",
      "@@@STEP_LOG_LINE@proto.output@}@@@",
      "@@@STEP_LOG_END@proto.output@@@"
    ]
  },
  {
    "cmd": [
      "led",
      "launch"
    ],
    "env": {
      "SWARMING_TASK_ID": null
    },
    "name": "led launch",
    "stdin": "{\n\"buildbucket\": {\n\"bbagent_args\": {\n\"build\": {\n\"builder\": {\n\"bucket\": \"try\", \n\"builder\": \"linux_warmed\", \n\"project\": \"chromium\"\n}, \n\"scheduling_timeout\": \"3600s\"\n}\n}, \n\"name\": \"led: warm linux_warmed\"\n}\n}",
    "~followup_annotations": [
      "@@@STEP_LOG_LINE@json.output@{@@@",
      "@@@STEP_LOG_LINE@json.output@  \"swarming\": {@@@",
      "@@@STEP_LOG_LINE@json.output@    \"host_name\": \"chromium-swarm.appspot.com\", @@@",
      "@@@STEP_LOG_LINE@json.output@    \"task_id\": \"fake-task-id\"@@@",
      "@@@STEP_LOG_LINE@json.output@  }@@@",
      "@@@STEP_LOG_LINE@json.output@}@@@",
      "@@@STEP_LOG_END@json.output@@@",
      "@@@STEP_LINK@Swarming task@https://chromium-swarm.appspot.com/task?id=fake-task-id@@@"
    ]
  },
  {
    "cmd": [
      "led",
      "launch"
    ],
    "env": {
      "SWARMING_TASK_ID": null
    },
    "name": "led launch (2)",
    "stdin": "{\n\"buildbucket\": {\n\"bbagent_args\": {\n\"build\": {\n\"builder\": {\n\"bucket\": \"try\", \n\"builder\": \"linux_warmed\", \n\"project\": \"chromium\"\n}, \n\"scheduling_timeout\": \"3600s\"\n}\n}, \n\"name\": \"led: warm linux_warmed\"\n}\n}",
    "~followup_annotations": [
      "@@@STEP_LOG_LINE@json.output@{@@@",
      "@@@STEP_LOG_LINE@json.output@  \"swarming\": {@@@",
      "@@@STEP_LOG_LINE@json.output@    \"host_name\": \"chromium-swarm.appspot.com\", @@@",
      "@@@STEP_LOG_LINE@json.output@    \"task_id\": \"fake-task-id\"@@@",
      "@@@STEP_LOG_LINE@json.output@  }@@@",
      "@@@STEP_LOG_LINE@json.output@}@@@",
      "@@@STEP_LOG_END@json.output@@@",
      "@@@STEP_LINK@Swarming task@https://chromium-swarm.appspot.com/task?id=fake-task-id@@@"
    ]
  },
  {
    "name": "$result"
  }
]