[
  {
    "cmd": [
      "python",
      "-u",
      "RECIPE_PACKAGE_REPO[depot_tools]/gerrit_client.py",
      "changes",
      "--host",
      "https://boringssl-review.googlesource.com",
      "--json_file",
      "/path/to/tmp/json",
      "--limit",
      "1",
      "-p",
      "change=123456",
      "-o",
      "ALL_REVISIONS",
      "-o",
      "DOWNLOAD_COMMANDS"
    ],
    "env": {
      "PATH": "<PATH>:RECIPE_PACKAGE_REPO[depot_tools]"
    },
    "infra_step": true,
    "name": "gerrit fetch current CL info",
    "~followup_annotations": [
      "@@@STEP_LOG_LINE@json.output@[@@@",
      "@@@STEP_LOG_LINE@json.output@  {@@@",
      "@@@STEP_LOG_LINE@json.output@    \"branch\": \"master\", @@@",
      "@@@STEP_LOG_LINE@json.output@    \"revisions\": {@@@",
      "@@@STEP_LOG_LINE@json.output@      \"184ebe53805e102605d11f6b143486d15c23a09c\": {@@@",
      "@@@STEP_LOG_LINE@json.output@        \"_number\": \"7\", @@@",
      "@@@STEP_LOG_LINE@json.output@        \"ref\": \"refs/changes/56/123456/7\"@@@",
      "@@@STEP_LOG_LINE@json.output@      }@@@",
      "@@@STEP_LOG_LINE@json.output@    }@@@",
      "@@@STEP_LOG_LINE@json.output@  }@@@",
      "@@@STEP_LOG_LINE@json.output@]@@@",
      "@@@STEP_LOG_END@json.output@@@"
    ]
  },
  {
    "cmd": [
      "python",
      "-u",
      "RECIPE_MODULE[depot_tools::bot_update]/resources/bot_update.py",
      "--spec-path",
      "cache_dir = '[CACHE]/git'\nsolutions = [{'deps_file': 'util/bot/DEPS', 'managed': True, 'name': 'boringssl', 'url': 'https://boringssl.googlesource.com/boringssl.git'}]",
      "--patch_root",
      "boringssl",
      "--revision_mapping_file",
      "{}",
      "--git-cache-dir",
      "[CACHE]/git",
      "--cleanup-dir",
      "[CLEANUP]/bot_update",
      "--output_json",
      "/path/to/tmp/json",
      "--patch_ref",
      "https://boringssl.googlesource.com/boringssl@refs/changes/56/123456/7",
      "--revision",
      "boringssl@HEAD"
    ],
    "env_suffixes": {
      "PATH": [
        "RECIPE_PACKAGE_REPO[depot_tools]"
      ]
    },
    "infra_step": true,
    "name": "bot_update",
    "~followup_annotations": [
      "@@@STEP_TEXT@Some step text@@@",
      "@@@STEP_LOG_LINE@json.output@{@@@",
      "@@@STEP_LOG_LINE@json.output@  \"did_run\": true, @@@",
      "@@@STEP_LOG_LINE@json.output@  \"fixed_revisions\": {@@@",
      "@@@STEP_LOG_LINE@json.output@    \"boringssl\": \"HEAD\"@@@",
      "@@@STEP_LOG_LINE@json.output@  }, @@@",
      "@@@STEP_LOG_LINE@json.output@  \"manifest\": {}, @@@",
      "@@@STEP_LOG_LINE@json.output@  \"patch_failure\": false, @@@",
      "@@@STEP_LOG_LINE@json.output@  \"patch_root\": \"boringssl\", @@@",
      "@@@STEP_LOG_LINE@json.output@  \"properties\": {}, @@@",
      "@@@STEP_LOG_LINE@json.output@  \"root\": \"boringssl\", @@@",
      "@@@STEP_LOG_LINE@json.output@  \"source_manifest\": {@@@",
      "@@@STEP_LOG_LINE@json.output@    \"directories\": {}, @@@",
      "@@@STEP_LOG_LINE@json.output@    \"version\": 0@@@",
      "@@@STEP_LOG_LINE@json.output@  }, @@@",
      "@@@STEP_LOG_LINE@json.output@  \"step_text\": \"Some step text\"@@@",
      "@@@STEP_LOG_LINE@json.output@}@@@",
      "@@@STEP_LOG_END@json.output@@@"
    ]
  },
  {
    "cmd": [
      "python",
      "-u",
      "RECIPE_PACKAGE_REPO[depot_tools]/gclient.py",
      "runhooks"
    ],
    "cwd": "[START_DIR]/boringssl",
    "env_suffixes": {
      "PATH": [
        "RECIPE_PACKAGE_REPO[depot_tools]"
      ]
    },
    "name": "gclient runhooks"
  },
  {
    "cmd": [
      "python",
      "-u",
      "[START_DIR]/boringssl/util/bot/go/env.py",
      "go",
      "run",
      "doc.go",
      "-out",
      "[TMP_BASE]/boringssl-docs_tmp_1"
    ],
    "cwd": "[START_DIR]/boringssl/util",
    "name": "generate"
  },
  {
    "jsonResult": null,
    "name": "$result"
  }
]